setup.py
src/stse/Binarizer.py
src/stse/__init__.py
src/stse/bytes_vect.py
src/stse/database.py
src/stse/dataframes.py
src/stse/dev_tools.py
src/stse/dictionaries.py
src/stse/duplicates.py
src/stse/error_checking.py
src/stse/plotting.py
src/stse/stats.py
src/stse/styling.py
src/stse/web.py
src/stse.egg-info/PKG-INFO
src/stse.egg-info/SOURCES.txt
src/stse.egg-info/dependency_links.txt
src/stse.egg-info/requires.txt
src/stse.egg-info/top_level.txt
src/test/__init__.py
src/test/test_binarizer.py
src/test/test_bytes_vect.py
src/test/test_database.py
src/test/test_dataframes.py
src/test/test_duplicates.py
src/test/test_web.py