Metadata-Version: 2.1
Name: stse
Version: 0.1.66
Summary: Various extremely useful and commonly needed functions
Home-page: https://github.com/jwgerlach00/stuff_that_should_exist
Author: Jacob Gerlach
Author-email: jwgerlach00@gmail.com
License: MIT
Platform: UNKNOWN
